build_model/__init__.py
build_model/test.py
wxaiprocdata-0.0.1.dist-info/METADATA
wxaiprocdata-0.0.1.dist-info/WHEEL
wxaiprocdata-0.0.1.dist-info/top_level.txt
wxaiprocdata-0.0.1.dist-info/RECORD
