Metadata-Version: 2.1
Name: wxaiprocdata
Version: 0.0.1
Summary: python 工具库、公共库
Author: liudaiyi
Author-email: 121274222@qq.com
Classifier: Programming Language :: Python :: 3
Classifier: License :: OSI Approved :: MIT License
Classifier: Operating System :: OS Independent
Requires-Python: >=3.6
